{
  "id": "ch04-ex06-slices-intro",
  "title": "The Slice Type - Views Into Data",
  "description": "Learn to use string slices and array slices to create efficient views into data without taking ownership",
  "chapter": 4,
  "exercise_number": 6,
  "difficulty": "beginner",
  "estimated_time_minutes": 20,
  "concepts": ["string_slices", "array_slices", "slice_syntax", "borrowing_slices"],
  "prerequisites": ["ch04-ex05-borrowing-rules"],
  "exercise_type": "code_completion",
  "rust_book_refs": {
    "primary_chapter": "4.3",
    "supporting_chapters": ["4.2"],
    "specific_sections": [
      {
        "chapter": "4.3",
        "title": "The Slice Type",
        "url": "https://doc.rust-lang.org/book/ch04-03-slices.html",
        "relevance": "core_concept"
      }
    ]
  },
  "hints": {
    "available": 3,
    "auto_unlock": false
  },
  "testing": {
    "timeout_seconds": 10,
    "memory_limit_mb": 50,
    "allow_std_only": true,
    "custom_checks": []
  },
  "validation": {
    "clippy_level": "warn",
    "format_required": true,
    "custom_checks": []
  }
}